{
  "symbol": "CAT",
  "quarter": "2024Q3",
  "transcript": [
    {
      "speaker": "Ryan Fiedler",
      "title": "Vice President of Investor Relations",
      "content": "Thanks, Audra. Good morning, everyone, and welcome to Caterpillar's third quarter of 2024 earnings call. I'm Ryan Fiedler, Vice President of Investor Relations. Joining me today are Jim Umpleby, Chairman and CEO; Andrew Bonfield, Chief Financial Officer; Kyle Epley, Senior Vice President of the Global Finance Services Division; Alex Kapper, Vice President-Elect of IR; and Rob Rengel, Senior Director of IR. During our call, we'll be discussing the third quarter earnings release we issued earlier today. You can find our slides, the news release, and a webcast recap at investors.caterpillar.com under Events & Presentations. The content of this call is protected by US and international copyright law. Any rebroadcast, retransmission, reproduction or distribution of all or part of this content without Caterpillar's prior written permission is prohibited. Moving to Slide 2. During our call today, we'll make forward-looking statements, which are subject to risks and uncertainties. We'll also make assumptions that could cause our actual results to be different than the information we're sharing with you on this call. Please refer to our recent SEC filings and the forward-looking statements reminder in the news release for details on factors that, individually or in aggregate, could cause our actual results to vary materially from our forecast. A detailed discussion of the many factors that we believe may have a material effect on our business on an ongoing basis is contained in our SEC filings. On today's call, we'll also refer to non-GAAP numbers. For a reconciliation of any non-GAAP numbers to the appropriate US GAAP numbers, please see the appendix of the earnings call slides. Now, let's turn to Slide 3 and turn the call over to our Chairman and CEO, Jim Umpleby.",
      "sentiment": "0.1"
    },
    {
      "speaker": "Jim Umpleby",
      "title": "Chairman and CEO",
      "content": "Thanks, Ryan. Good morning, everyone. Thank you for joining us. As we close out the third quarter, I want to thank our global team for another good quarter as our results reflect the benefit of the diversity of our end markets. We delivered strong adjusted operating profit margin and adjusted profit per share, which were consistent with our expectations, although our top-line was lower than we anticipated. We also generated ME&T free cash flow of $2.7 billion in the third quarter. Our robust ME&T free cash flow, along with our strong balance sheet, allowed us to deploy over $9 billion to shareholders through share repurchases and dividends during the first three quarters of the year, including $1.5 billion this quarter. We continue to remain disciplined in the execution of our strategy for long-term profitable growth. I'll begin with my perspectives about our performance in the quarter and will provide an update on our full year expectations. I'll then provide some insights about our end markets, followed by an update on our strategy and sustainability journey. Moving to quarterly results. Sales and revenues were down 4% in the third quarter versus last year, below our expectations due to the impact of lower-than-expected sales to users in Construction Industries and timing of deliveries in Resource Industries and Energy & Transportation. Services increased in the quarter compared to 2023. Adjusted operating profit margin was generally in line with our expectations at 20%. We achieved quarterly adjusted profit per share of $5.17, in line with our expectations at the time of the last earnings call. In addition, our backlog increased slightly to $28.7 billion and remains at a very healthy level. For the full year, although we updated our expectations since our last earnings call to reflect sales being slightly below our prior estimate, our expected adjusted operating profit margin is unchanged and remains above the top of the range. Also, our expectation for adjusted profit per share is unchanged. We are increasing our expectations for ME&T free cash flow and now anticipate it will be near the top of our target range of $5 billion to $10 billion. Turning to Slide 4. In the third quarter of 2024, sales and revenues declined 4% to $16.1 billion due to lower sales volume. Compared to the third quarter of 2023, overall sales to users decreased 6%. For Machines, which includes Construction Industries and Resource Industries, sales to users declined by 10%, which was below our expectations. Energy & Transportation continued to grow as sales to users increased 5%. Sales to users in Construction Industries were down 7% year-over-year. In North America, sales to users were down primarily due to lower rental fleet loading and the absence of a large pipeline deal in the third quarter of 2023. Excluding these two items, sales to users were about flat versus the prior year. Compared to our expectations, sales to users were lower than expected, impacted by rental fleet loading. Our dealers' rental revenue continued to grow in the quarter. Sales to users declined in EAME, primarily due to ongoing weakness in construction activity in Europe. Sales to users in Asia Pacific declined, while Latin America increased. In Resource Industries, sales to users declined 18%, generally in line with our expectations versus a strong third quarter in 2023. Mining, as well as heavy construction, and quarry and aggregates were lower, mainly due to softness we previously discussed for two products, articulated trucks and off-highway trucks. In Energy & Transportation, sales to users increased by 5%, and we continue to see growth in all applications except industrial. Power generation sales to users grew strongly as market conditions remained favorable for both reciprocating engines and solar turbines and turbine-related services. Oil and gas sales to users benefited from strong sales of turbines and turbine-related services. For reciprocating engines in oil and gas applications, sales to users were higher for gas compression but lower in well servicing. Transportation sales to users increased, while industrial declined as we expected. Our results continue to reflect the benefit of the diversity of our end markets, as well as the disciplined execution of our strategy for long-term profitable growth. Moving to dealer inventory and our backlog. In total, dealer inventory increased by $400 million versus the second quarter of 2024. For Machines, dealer inventory increased by $100 million, slightly more than we had anticipated. Looking ahead to the fourth quarter, our current planning assumptions forecast a reduction in machine dealer inventory, and we expect machine dealer inventory to end the year around the same level as year-end 2023. Dealers are independent businesses and make stocking decisions across a wide range of products based on multiple factors across the product portfolio. While machine dealer inventory is currently around the top end of the typical range, we remain comfortable with the overall level of dealer inventory. As I mentioned, backlog increased slightly versus the second quarter to $28.7 billion. Energy & Transportation increased as we continue to see strong demand for solar turbines in oil and gas and power generation, as well as strong demand for reciprocating engines for power generation. Moving to Slide 5, we generated robust ME&T free cash flow of $2.7 billion in the third quarter and $6.4 billion in the first three quarters of 2024. As I mentioned, year-to-date, we deployed more than $9 billion to shareholders through share repurchases and dividends. We remain proud of our dividend aristocrat status and continue to expect to return substantially all ME&T free cash flow to shareholders over time through dividends and share repurchases. Now, on Slide 6, I'll describe our expectations for our three primary segments moving forward. In Construction Industries, we expect lower sales to users in the fourth quarter, but remain positive about the longer-term demand outlook. During our August earnings call, we noted a lower level of rental fleet loading in North America, which continued into the third quarter, and we now expect the trend to persist in the fourth quarter. Although we have lowered our expectations for sales to users in the fourth quarter, primarily due to lower rental fleet loading, dealer rental revenue continues to grow. In addition, government-related infrastructure projects are expected to remain healthy, supported by funding yet to be spent from the IIJA. In Asia Pacific, outside of China, we expect soft economic conditions to continue. We anticipate demand in China will remain at a relatively low level for the above 10-ton excavator industry. In EAME, we anticipate that weak economic conditions in Europe will continue, partially offset by continued healthy construction demand in the Middle East. Construction activity in Latin America remains healthy, and we are expecting modest growth to continue. In addition, we expect the ongoing benefit of our services initiatives will positively impact Construction Industries. Next, I'll discuss Resource Industries. After strong performance in 2023 in mining as well as heavy construction and quarry and aggregates, we continue to anticipate lower machine volume in the fourth quarter of 2024 versus last year. However, the rate of decline for sales to users in the fourth quarter is expected to moderate versus the previous quarters. We expect to see higher services revenues, including robust rebuild activity. Customer product utilization remains high, the number of parked trucks remains relatively low, the age of the fleet remains elevated, and our autonomous solutions continue to see strong customer acceptance. Customers continue to display capital discipline. However, we continue to believe the energy transition will support increased commodity demand over time, expanding our total addressable market and providing further opportunities for long-term profitable growth. Moving to Energy & Transportation. For power generation, demand is expected to remain strong, and we expect robust growth in the fourth quarter and full year sales for both reciprocating engines and solar turbines. Overall strength in power generation continues to be driven by data center growth related to cloud computing and generative AI, and we expect this trend to continue. In oil and gas, in total, we continue to expect a stronger year overall in 2024 versus 2023. For solar turbines used in oil and gas applications, we expect a strong fourth quarter, but sales are expected to be lower than the fourth quarter of 2023 due to the timing of deliveries. The increase in power generation at solar will mostly offset solar's decline in oil and gas, so we expect solar's total sales in the fourth quarter to be roughly flat compared to last year. Solar has a strong backlog as well as healthy order and inquiry activity, and we continue to expect full year growth for solar in oil and gas. After a strong 2023, we expect reciprocating engine sales in oil and gas to be slightly down this year, primarily due to ongoing softness in well servicing. We still expect gas compression to be up for the full year. However, we expect it to soften in the near term as equipment lead times have normalized. As we had previously mentioned, we can leverage our large engine platforms across a variety of applications. Based on current market conditions and well servicing applications, we are able to serve additional power generation demand as we continue to meet oil and gas customer needs while optimizing our overall large engine capacity. Industrial demand has continued to remain at a relatively low level compared to 2023. In transportation, we anticipate full year growth in both rail services and marine applications. Moving to Slide 7, now, I'll provide an update on our strategy and sustainability journey. In February of 2024, we announced a multiyear capital investment in our large reciprocating engine division to approximately double output capability compared to 2023 for new engines and aftermarket parts. Based on increasing expectations of future demand growth, today, we are announcing an additional multiyear investment to further expand our large engine volume output capability to more than 125% compared to 2023. As I mentioned, we leverage these large engines across a variety of applications, including data centers, oil and gas, large mining trucks, and distributed power generation. Moving on to sustainability. We continue to invest in new products, technologies and services to help our customers achieve their climate-related objectives. In September, we unveiled an innovative solution to help solve one of the most complex aspects of the mining industry's energy transition, energy management. Cat Dynamic Energy Transfer, or DET, is a fully Caterpillar developed system that can transfer energy to both diesel electric and battery electric large mining trucks while they are working around them on-site. It can also charge batteries while operating with increased speed on grade, improving operational efficiency and machine uptime. Cat DET is comprised of a series of integrated elements, including a power module that converts energy from a mine site's power source, an electrified rail system to transmit the energy, and a machine system to transfer the energy to the truck's powertrain. Cat DET will integrate with the Cat MineStar Command for hauling solution, merging autonomy and electrification technologies to provide a holistic site solution. We believe mine sites will benefit from enhanced efficiency with the integration of electrification and automation. When combined, these technologies will help miners achieve production targets, while simultaneously managing energy demands. This example highlights how we leverage our industry-leading technology through an integrated approach across our portfolio to help our customers build a better, more sustainable world. With that, I'll turn it over to Andrew.",
      "sentiment": "0.5"
    },
    {
      "speaker": "Andrew Bonfield",
      "title": "Chief Financial Officer",
      "content": "Thank you, Jim, and good morning, everyone. As usual, I'll begin with a high-level summary of the third quarter, and then provide more detailed comments, including the performance of the segments. I'll then, discuss the balance sheet and free cash flow, before concluding with comments on our assumptions for the full year and the fourth quarter. Beginning on Slide 8, although sales and revenues were lower than we had expected, our adjusted operating profit margin was 20.0%, generally in line with what we had anticipated. Adjusted profit per share was in line with our expectations despite adjusted operating profit being impacted by the lower sales and revenues. I will highlight a few of the moving parts in a moment. As Jim mentioned, our full year margin expectations remain unchanged, and we continue to anticipate the adjusted operating profit margin will be above the top end of the target range despite the slightly lower outlook for the top-line. Our expectations for adjusted profit per share remain unchanged versus our expectations at the time of our last earnings call. Also, we have increased our expectations for ME&T free cash flow for the year, which we now anticipate will be near the top of our $5 billion to $10 billion target range. In the third quarter, sales and revenues of $16.1 billion decreased by 4% compared to the prior year. The adjusted operating profit margin of 20.0% was 80 basis points lower when compared to the prior year. Profit per share was $5.06 in the third quarter compared to $5.45 in the third quarter of last year. Restructuring costs were $0.11 in the quarter versus $0.07 in the prior year. Adjusted profit per share was $5.17 in the quarter compared to $5.52 last year. Other income and expense was $119 million headwind versus the prior year, mostly driven by an unfavorable currency impact related to ME&T balance sheet translation. We do not forecast the impact of foreign currency translation on our adjusted profit per share, so this acted as a headwind compared to our expectations for the quarter. Excluding discrete items, the provision for income taxes in the third quarter in both 2023 and 2024 reflected a global annual effective tax rate of 22.5%. We recorded a discrete tax benefit, which had a $0.11 favorable impact within the quarter. We do not anticipate discrete items. Finally, the year-over-year impact from the reduction in the average number of shares outstanding, primarily due to share repurchases, resulted in a favorable impact on adjusted profit per share of approximately $0.26 as compared to the third quarter 2023. This was slightly better than we had expected. Moving to Slide 9, I'll discuss our top-line results for the third quarter. Sales and revenues decreased by 4% compared to the prior year, primarily impacted by lower sales volume as a result of lower sales to users and impacts from changes in dealer inventories. Total sales to users decreased by 6% as a 10% decrease from Machines was partially offset by a 5% increase for Energy & Transportation. The impact from changes in total dealer inventories acted as a sales headwind of about $200 million in the quarter. For Machines-only, dealer inventory increased by about $100 million, a smaller increase than the $400 million increase in the prior year, but slightly above our expectations of being flattish to slightly lower. Service revenues increased versus the prior year, as we had anticipated. Moving to operating profit on Slide 10. Operating profit in the third quarter decreased by 9% to $3.1 billion. Adjusted operating profit decreased by 8% to $3.2 billion, mainly due to the impact of lower sales volume, partially offset by favorable price realization and manufacturing costs. Since early 2022, price realization has been strong and often exceeded our expectations. Over the past several quarters, we have highlighted that price will begin to moderate in the second half of this year. In the third quarter, this moderation began to occur as price realization was lower than previous quarters and generally in line with our expectations. As I mentioned, for the third quarter, the adjusted operating profit margin was 20.0%, which was generally in line with our expectations. By segment, margin in Construction Industries and Resource Industries was slightly below our expectations on lower volume, while Energy & Transportation was about in line. Financial products had a slightly stronger quarter than we had expected. On Slide 11, Construction Industries sales decreased by 9% in the third quarter to $6.3 billion, slightly below our expectations. The decrease versus the prior year was primarily due to lower sales volume and unfavorable price realization. The decrease in sales volume was mainly driven by lower sales of equipment to end users. Changes in dealer inventories also acted as a slight headwind to sales. By region, Construction Industries sales in North America decreased by 11%; in Latin America, sales increased by 19%; sales in the EAME region decreased by 15%; in Asia Pacific, sales declined by 12%. Third quarter profit for Construction Industries was $1.5 billion, a 20% decrease versus the prior year. This is mainly due to the profit impact of lower sales volume and unfavorable price realization. The segment's margin of 23.4% was a decrease of 300 basis points versus the prior year. Turning to Slide 12, Resource Industries sales decreased by 10% in the third quarter to $3.0 billion, which was slightly below our expectations. The decline versus the prior year was primarily due to lower sales volume, mainly driven by lower sales of equipment to end users given a challenging comparison to the prior year. Third quarter profit for Resource Industries decreased by 15% versus the prior year to $619 million. This was mainly due to the profit impact of lower sales volume. The segment's margin of 20.4% was a decrease of 140 basis points versus the prior year. Now, on Slide 13, Energy & Transportation sales increased by 5% in the third quarter to $7.2 billion, slightly lower than we had expected, driven by the timing of deliveries. The increase versus the prior year was primarily due to favorable price realization and higher sales volume, including higher intersegment sales. By application, power generation sales increased by 26%, transportation sales were higher by 3%, oil and gas sales decreased by 1%, and industrial sales decreased by 16%. Third quarter profit for Energy & Transportation increased by 21% versus the prior year to $1.4 billion. The increase was mainly due to favorable price realization. The segment's margin of 19.9% was an increase of 270 basis points versus the prior year. Moving to Slide 14, financial products revenues increased by 6% to about $1 billion, primarily due to higher average earning assets driven by North America and higher average financing rates across all regions. Segment profit increased by 21% to $246 million. This is mainly due to a favorable impact from equity securities and a lower provision for credit losses. Our customers' financial health is strong. Past dues remain near historic lows of 1.74% in the quarter, down 22 basis points versus the prior year. Our allowance rate was 0.87%, our lowest on record. Business activity at Cat Financial remains healthy. Our retail new business volume increased by 17% versus the prior year, supported by our financing packages for customers choosing to buy Caterpillar equipment. Though Caterpillar's retail machine sales volume was lower, proportionately more sales have been financed through Cat Financial, which highlights the attractiveness of the financing options we are offering to our customers. We also continue to see healthy demand for used equipment and inventories remain at low levels. Conversion rates are also strong as customers choose to buy equipment at the end of their lease term. Moving on to Slide 15, we generated about $2.7 billion in ME&T free cash flow in the third quarter and deployed about $1.5 billion in share repurchases and dividends. Our balance sheet remains strong with an enterprise cash balance of $5.6 billion. In addition, we hold $1.8 billion in slightly longer dated liquid marketable securities to improve yields on that cash. Now, on Slide 16, I will share our high-level assumptions for the full year. For the full year, we have updated our outlook to reflect sales and revenues that are slightly lower than our expectations at the time of our last earnings call, driven by lower-than-expected third quarter sales and an update to our expectations for dealer rental fleet loading in Construction Industries. We continue to anticipate services growth in 2024. As I mentioned earlier, our full year expectations for adjusted operating profit margin and adjusted profit per share remain unchanged compared to our last earnings call. We continue to expect adjusted operating profit margin to be above the top end of the target range. In addition, we are increasing our expectations for ME&T free cash flow for the year, which we now anticipate to be near the top of our $5 billion to $10 billion target range. To assist you with your modeling for the full year, we now anticipate CapEx of around $2 billion and restructuring costs of approximately $400 million. Our expectation for the global annual effective tax rate, excluding discrete items, remains at 22.5%. Turning to Slide 17, I'll provide a few comments on the fourth quarter, starting with the top-line. We expect slightly lower sales and revenues in the fourth quarter compared to the prior year, impacted by lower machine sales to users versus a strong comparison. On machine dealer inventory, our planning assumptions include the expectation that dealers will reduce their inventories in the fourth quarter while balancing their need to be prepared for 2025. The magnitude of the decline for machine dealer inventory is expected to be less than the $1.4 billion decrease we saw in the fourth quarter of 2023. For perspective, we expect machine dealer inventory to end the year around the same level as year-end 2023. Also, the ongoing benefit of our services initiatives is expected to positively impact sales in the fourth quarter. By segment, in the fourth quarter, compared to the prior year, we anticipate a sales decrease in Construction Industries. This is impacted by lower sales to users, which Jim mentioned, along with unfavorable price realization. In Resource Industries, we expect slightly lower sales, impacted by lower sales to users versus a strong fourth quarter of 2023. In Energy & Transportation, we anticipate slightly higher sales versus the prior year, supported by power generation. Enterprise margin in the fourth quarter is expected to trend lower compared to the third quarter, following the typical seasonal pattern. However, versus the prior year, we expect a modestly higher adjusted operating profit margin despite lower sales. We anticipate favorable manufacturing costs and lower SG&A and R&D expenses will more than offset the profit impact of lower sales volume. Lower SG&A and R&D expenses are primarily driven by the benefit of lower short-term incentive compensation versus a high expense in the prior year quarter. Price realization for Machines is expected to trend lower as the pricing environment continues to normalize, though price in Energy & Transportation should act as a partial offset. Regarding price expectations for Machines, it is important to note that discounts to dealers occur through post-sales merchandising programs, which impact our results over time. This includes financing support from Cat Financial, which is an effective way of supporting our customers, and we recover a portion of that support over the life of the deal. Let me explain. Based on the current level of price discounting support, we reserve the anticipated payments to dealers for these merchandising programs. At times, there is a lag between the timing of the invoice of the dealer and when the dealer invoices the customer, which impacts the reserve. Over the next few quarters, we expect the impact from these merchandising programs to drive a headwind to Machine price realization as we continue to adjust the reserve to reflect the current level of price discounting support. By segment, in the fourth quarter, in Construction Industries, we anticipate lower margin compared to the prior year primarily due to unfavorable price realization, partially offset by favorable manufacturing costs. In Resource Industries, we anticipate lower margin in the fourth quarter compared to the prior year, mainly due to lower volume and prioritization of strategic investments around services growth and AACE, which is autonomy, alternative fuels, connectivity and digital, and electrification. Favorable manufacturing costs should act as a partial offset. In Energy & Transportation, we expect a higher margin versus the prior year, primarily impacted by favorable price realization. So, turning to Slide 18, let me summarize. Although sales and revenues were lower than we had expected, adjusted operating profit margin and adjusted profit per share were generally in line with our expectations. We now anticipate our top-line for the full year will be slightly below our prior estimate. Our backlog increased slightly and remains at a very healthy level. Our expectations for full-year adjusted operating profit margin and adjusted profit per share remain unchanged compared to a quarter ago. We continue to expect adjusted operating profit margin to be above the top end of the target range for the full year based on our expected sales levels. We are now increasing our expectations for ME&T free cash flow, which we anticipate to be near the top of our target range for the full year. Our team executed well in the quarter, and our results continue to benefit \u2014 to reflect the benefit of the diversity of our end markets and the disciplined execution of our strategy for long-term profitable growth. And with that, we'll now take your questions.",
      "sentiment": "0.3"
    },
    {
      "speaker": "Operator",
      "title": "Operator",
      "content": "Thank you. We will now begin the question-and-answer session. We'll take our first question from Jerry Revich at Goldman Sachs.",
      "sentiment": "0.0"
    },
    {
      "speaker": "Jerry Revich",
      "title": "Analyst",
      "content": "Yes. Hi. Good morning, everyone.",
      "sentiment": "0.0"
    },
    {
      "speaker": "Jim Umpleby",
      "title": "Chairman and CEO",
      "content": "Good morning, Jerry.",
      "sentiment": "0.0"
    },
    {
      "speaker": "Jerry Revich",
      "title": "Analyst",
      "content": "Hi. I'm curious if we could take a moment to discuss your margin performance this year, which is impressive compared to your long-term targets. Do you believe this level of outperformance can be maintained, or should we interpret the pricing challenges mentioned in the prepared remarks as an indication that you are reconsidering the best balance between margins and market share?",
      "sentiment": "0.1"
    },
    {
      "speaker": "Jim Umpleby",
      "title": "Chairman and CEO",
      "content": "Well, Jerry, just as a reminder, our primary measure of profitable growth is increasing absolute OPACC dollars. That's something we're very focused on. Obviously, we're always focused on being competitive in the various markets that we serve, and of course, we serve a diverse group of industries around the world. So, what's happening in one market with one segment can be very different than what's happening in another segment just from a competitive perspective. So, again, we're focused on remaining competitive. We do provide margin targets, obviously, to give investors and analysts a sense of where we'll be around margins, and we'll continue to do that. So, again, we're driving to remain competitive, we're driving to increase absolute OPACC dollars, and you can use our margin target ranges to give a sense of where we expect to be.",
      "sentiment": "0.3"
    },
    {
      "speaker": "Operator",
      "title": "Operator",
      "content": "We'll move next to Tami Zakaria at JPMorgan.",
      "sentiment": "0.0"
    },
    {
      "speaker": "Jim Umpleby",
      "title": "Chairman and CEO",
      "content": "Good morning, Tami.",
      "sentiment": "0.0"
    },
    {
      "speaker": "Tami Zakaria",
      "title": "Analyst",
      "content": "Hi. Good morning, Team Caterpillar. Hope you're doing well. My question is on the Resource Industries segment. Volumes in that segment has been down for about a year now, and I think you said the rate of decline you expect to get better in the fourth quarter. I'm curious, how are you planning for this segment for 2025? Do you expect demand or sales to stabilize near term or could it get better or maybe stay weak for a few more quarters?",
      "sentiment": "0.1"
    },
    {
      "speaker": "Jim Umpleby",
      "title": "Chairman and CEO",
      "content": "Well, thanks for your question. I mean, the full year drop, as we talked about in previous calls, is really primarily due to a couple of products, articulated trucks and off-highway trucks. And we had a strong backlog there that we had to work our way through, and that's created a comp issue for us in Resource Industries this year. Having said that, obviously, we're not going to give guidance around 2025. We'll talk about 2025 in January, but certainly, we continue to be quite bullish on the long-term aspects of mining just given all the commodities that need to be produced to support the energy transition. Our mining customers use our products to produce those products, things like copper. So, our customers are displaying capital discipline, but we certainly are bullish about the long term. We do expect higher services revenues because the utilization of our products is quite high. The age of the fleet is relatively elevated, and the number of parked trucks is relatively low. So, those are all positive things. One of the things that we also see is a lot of inquiry activity and order activity around large mining trucks, so we're pleased with that. So that's one of the things that also is a reason for optimism as well.",
      "sentiment": "0.4"
    },
    {
      "speaker": "Operator",
      "title": "Operator",
      "content": "Next, we'll move to Angel Castillo at Morgan Stanley.",
      "sentiment": "0.0"
    },
    {
      "speaker": "Angel Castillo",
      "title": "Analyst",
      "content": "Hi, good morning. Thanks for taking my question. I was wondering if you could expand maybe a little bit...",
      "sentiment": "0.0"
    },
    {
      "speaker": "Jim Umpleby",
      "title": "Chairman and CEO",
      "content": "Hi, Angel.",
      "sentiment": "0.0"
    },
    {
      "speaker": "Angel Castillo",
      "title": "Analyst",
      "content": "Good morning. I was wondering if you could expand a little bit more on what you're hearing from your dealers and customers around in terms of Construction Industries, particularly in terms of orders, how is that kind of shaking out for that segment specifically? And then more so qualitatively what you're hearing into 2025 in terms of sentiment and kind of inclinations to buy kind of heading into that year versus the macro that remains a little bit uncertain?",
      "sentiment": "0.0"
    },
    {
      "speaker": "Jim Umpleby",
      "title": "Chairman and CEO",
      "content": "Yeah. Well, a couple of things. Firstly, in the quarter, as I mentioned earlier, the primary reasons for the decline quarter-to-quarter were based on lower rental fleet loading by our dealers. And, of course, it's important to note that our dealers' rental revenue continues to increase, so it's really an issue of them having lower loading into their rental fleets. In addition to that, we had a large pipeline deal in the third quarter of last year, which obviously didn't reoccur, and that created an issue as well. I mean, from a positive perspective, we expect government-related infrastructure to remain healthy. I mean, if we look at some facts from ARTBA, which is the American Road and Transportation Builders Association, they noted that only 27% of the $348 billion in total on IIJA funding has been spent as of August of 2024. About 47% of it's been committed, and only 27% of it's been spent. So that's quite healthy as well. So, there's a lot of infrastructure activity out there that our dealers are working with their customers to help support. So, we feel good about that as well.",
      "sentiment": "0.4"
    },
    {
      "speaker": "Operator",
      "title": "Operator",
      "content": "We'll go next to Jamie Cook at Truist Securities.",
      "sentiment": "0.0"
    },
    {
      "speaker": "Jamie Cook",
      "title": "Analyst",
      "content": "Hi, good morning. And I'm sorry, I'm flipping between multiple calls, but, Jim, I think you said during the prepared remarks that you guys are adding incremental large engine capacity relative to your previous announcement. So, I guess my question is, is there any way you can frame the capital investment? And more importantly, what you think the longer-term revenue opportunity for Caterpillar as you continue to increase capacity here? And then, sort of what does that imply for margins for this segment? Again, we're adding a lot of capacity, but the margins are below Resource and Construction. So, should margins be structurally higher as the volumes ramp? Thank you.",
      "sentiment": "0.3"
    },
    {
      "speaker": "Jim Umpleby",
      "title": "Chairman and CEO",
      "content": "Thanks for your question, Jamie. We haven't quantified the amount of capital investment in that capacity increase, but we did talk about the fact that we expect with this incremental investment that we will have increased our large engine volume output capability to more than 125% compared to 2023. And, of course, those engines are used across a wide variety of applications, and certainly, what's driving the demand today is data centers. We sell backup generator sets for data centers, but we're also quite excited about the opportunity going forward for what we call distributed generation. Data centers don't just create an opportunity for us for backup generator sets, but, of course, the base load requirements on the grid is going up as well because of data centers, and there's much been written about that. And so, just given the fact that there's been relative underinvestment in traditional power plants over the last few years, the fact that more renewables have been added to the grid, which are intermittent in nature, and the fact that now we have data centers increasing baseload requirements on the grid, we think that creates an opportunity for us for both our gas turbine generator sets and our reciprocating engine generator sets in what we call distributed power applications distributed across the grid, and our gas turbines and gensets can burn a wide variety of fuels, natural gas, biofuels, hydrogen blends. So, we're quite excited about that long-term opportunity that is starting to manifest itself. And your question about margins, certainly, you saw a nice margin increase quarter-to-quarter in Energy & Transportation, and just because of mix and because of increased volume and just the fact that business should be higher. Again, we have the opportunity to increase margins in Energy & Transportation going forward, but I'm not going to quantify that at this point. But certainly, it's an opportunity.",
      "sentiment": "0.5"
    },
    {
      "speaker": "Operator",
      "title": "Operator",
      "content": "We'll take our next question from David Raso at Evercore ISI.",
      "sentiment": "0.0"
    },
    {
      "speaker": "David Raso",
      "title": "Analyst",
      "content": "Hi. Thank you. Yeah, looking, as everybody, more breadcrumbs for 2025. My question, I guess, two pieces. The comment about the drag, right, the lag of discounting for CI. It'll show itself more as some of those orders get shipped into '25. Can you give us a sense of just where we stand right now? Let's assume no further deterioration maybe in CI pricing. But what we're booking right now with those discounts, what is the most acute, like, period in '25 that that shows up? Like, essentially, it's how long are these orders out for? Is this second quarter, third quarter next year, that should be the most acute drag from the incremental discounting right now? And then, on the positive side, you kind of just said you didn't want to quantify it, but the investments in E&T, the large engines, which I know also go to large mining trucks, but let's think of it as E&T in particular right now, is there any way to think about regular throughput improvement? Any capacity additions that can show up in '25 to give us a sense of at least your throughput capability '25 versus '24? Just some order of magnitude? Thank you.",
      "sentiment": "0.2"
    },
    {
      "speaker": "Jim Umpleby",
      "title": "Chairman and CEO",
      "content": "Thanks for your question, David. One of the points we made when we announced our initial investment to enhance our large engine capacity is that this would be a gradual increase over a four-year period. We haven't provided a breakdown year-by-year, so unfortunately, I can't give you an estimate of additional output for 2025. I'll let Andrew address your question regarding margins.",
      "sentiment": "0.1"
    },
    {
      "speaker": "Andrew Bonfield",
      "title": "Chief Financial Officer",
      "content": "On the impact of pricing, this is one of those accounting quirks we encounter. The accrual is performed on a historical 12-month basis to build up the reserve. Therefore, this could affect us for several quarters. As the merchandising programs expand, we have to address the inventory buildup over time, which is spread over a 12-month period. Generally, this will last for the next several quarters, but we are beginning to see the merchandising programs normalize, which creates a slight headwind on pricing. I will likely provide a clearer quantification during our guidance for 2025 in January.",
      "sentiment": "0.2"
    },
    {
      "speaker": "Operator",
      "title": "Operator",
      "content": "Next, we'll go to Michael Feniger at Bank of America.",
      "sentiment": "0.0"
    },
    {
      "speaker": "Michael Feniger",
      "title": "Analyst",
      "content": "Thank you for taking my question. I would like to understand the situation on the oil and gas front. Retail sales have seen a slight increase. You mentioned the differences observed in various sectors like the reciprocating side, well services, and possibly gas compression. Looking ahead to 2025, if there is an increase in LNG permitting in the Gulf, would that have a positive impact on the solar business? Is a higher natural gas price necessary? The oil price has been somewhat stagnant. I'm interested in how we should approach the strong oil and gas performance expected in 2024 and what insights can be shared regarding the outlook for 2025 in that sector. Thank you.",
      "sentiment": "0.2"
    },
    {
      "speaker": "Jim Umpleby",
      "title": "Chairman and CEO",
      "content": "I will refrain from providing guidance for 2025, but I can share some insights about the industry. We've noted that well servicing remains somewhat weak. For gas compression related to Cat oil and gas, we anticipate growth for the entire year, although we expect some decline in the fourth quarter. The business for solar turbines in the oil and gas sector is performing well, with substantial booking and quotation activity for both gas compression and international projects. Overall, the solar business is quite strong. Regarding LNG exports, if the permitting process resumes, it could be beneficial for us in the medium to long term.",
      "sentiment": "0.4"
    },
    {
      "speaker": "Operator",
      "title": "Operator",
      "content": "We'll move to our next question from Kristen Owen at Oppenheimer & Company.",
      "sentiment": "0.0"
    },
    {
      "speaker": "Kristen Owen",
      "title": "Analyst",
      "content": "Great. Thank you for taking the question. Jim, I wanted to come back to the CI competitive dynamics, particularly in North America. I mean, you've called out this re-fleeting issue a couple of quarters in a row now, but you are at the higher end of the inventory range. Just wondering, can you help us understand how much maybe incremental international competition you're seeing, given the depreciation at the yen and just continued disappointment in China activity? Is there anything you're seeing on a shift in the competitive landscape there?",
      "sentiment": "0.1"
    },
    {
      "speaker": "Jim Umpleby",
      "title": "Chairman and CEO",
      "content": "We are very focused on staying competitive, and the competitive landscape is constantly evolving. Throughout my time in this role and prior, the competitive environment has always changed, but we are confident in our ability to compete. We are actively investing in new technologies to help operators run their machines more effectively, enabling less experienced operators to perform at levels closer to their more seasoned counterparts. We are also enhancing our digital capabilities, and our dealers are doing the same. We believe we can continue to compete successfully. There are fluctuations in currency, such as the weakness of the yen, which can temporarily benefit competitors, but these situations change as currencies fluctuate. Ultimately, our primary focus is on providing long-term value to our customers through our ongoing investments in technology, digital capabilities, and services.",
      "sentiment": "0.4"
    },
    {
      "speaker": "Andrew Bonfield",
      "title": "Chief Financial Officer",
      "content": "And can I just make a comment on your comment about the higher end of the inventory range? I mean, one of the things just to remember is dealer inventory is complex. We have 150 dealers around the world. We have three business segments. We have lots of different products. There are some actual product lines where, actually, dealers holding more inventory would actually be a good thing from a competitive perspective, not necessarily always reducing. So, it's not necessarily without them burning it down. We obviously, work with them through that process where they do need to think about a deal inventory reduction, and that's why we're anticipating in the fourth quarter. But there are also some business segments where, actually, at times, we would like dealers probably to hold a little bit more for competitive reasons as well.",
      "sentiment": "0.2"
    },
    {
      "speaker": "Operator",
      "title": "Operator",
      "content": "We'll go next to Steven Fisher at UBS.",
      "sentiment": "0.0"
    },
    {
      "speaker": "Steven Fisher",
      "title": "Analyst",
      "content": "Thank you. Good morning. Jim, you talked about the four-year timeline for expanding power generation capacity, but we actually saw power generation growth accelerate to about 26% year-over-year, up from 15% in Q2. Given that we're at capacity for some of the larger projects, could you explain what caused this acceleration? To what extent might this be due to transitioning some of your oil and gas engines into power generation? Should we anticipate some quarter-to-quarter fluctuations in the growth rate of power generation moving forward, depending on comparisons and your ability to adjust capacity? Thank you.",
      "sentiment": "0.1"
    },
    {
      "speaker": "Jim Umpleby",
      "title": "Chairman and CEO",
      "content": "Thanks for your question. To clarify, when we ship a generator set to an oil and gas customer or for an oil and gas application, we categorize that as oil and gas, not power generation. There are various reasons for the increase. As I mentioned in my prepared remarks, we do have the capability to reallocate resources. If the demand for oil and gas decreases and we have excess capacity, we can transfer those engines between oil and gas and power generation based on our customers' needs. Additionally, our solar power generation business is also experiencing growth, which contributes to the overall increase. We are actively working in our reciprocating engine facilities to boost capacity. While the major impact from our significant capital investment will manifest later, we are also focused on improving throughput and maximizing output from our current facilities as demand rises.",
      "sentiment": "0.3"
    },
    {
      "speaker": "Operator",
      "title": "Operator",
      "content": "We'll take our next question from Kyle Menges of Citigroup.",
      "sentiment": "0.0"
    },
    {
      "speaker": "Kyle Menges",
      "title": "Analyst",
      "content": "Thanks for taking the question. I was hoping if you could discuss inventories a little bit more. So, this planned reduction in dealer inventories in 4Q, is that enough to make you guys feel pretty good about machine inventories heading into next year? And then, it'd also be helpful just to hear your thoughts on used inventories. Sounds like they remain at low levels, but are you seeing used tick up a little bit? And is there any cause for concern that used inventories could become an issue in 2025?",
      "sentiment": "0.1"
    },
    {
      "speaker": "Andrew Bonfield",
      "title": "Chief Financial Officer",
      "content": "First, regarding used inventory, it remains historically low, even if there has been a slight increase. Pricing has decreased a bit, but from Cat Financial's perspective, it's still acceptable. Overall, we are not concerned about used inventory at this time. On the topic of dealer inventory, we collaborate closely with our dealers through our sales and operations planning process, analyzing their expectations and ordering needs by dealer and product. This aids us in managing factory production effectively. Currently, we anticipate that the expected reduction will keep overall inventory levels flat year-over-year, which aligns with feedback from dealers. I don't foresee a need for significant further reductions at this time, though discussions on this will continue into 2025. We are prepared to manage production as required. Additionally, there are some product lines where dealers could actually hold more inventory. Therefore, we need to approach the situation carefully, but overall, we feel confident about the inventory levels and our expectations for year-end.",
      "sentiment": "0.2"
    },
    {
      "speaker": "Operator",
      "title": "Operator",
      "content": "We'll go next to Chad Dillard at Bernstein.",
      "sentiment": "0.0"
    },
    {
      "speaker": "Chad Dillard",
      "title": "Analyst",
      "content": "Hey. Good morning, all. So...",
      "sentiment": "0.0"
    },
    {
      "speaker": "Andrew Bonfield",
      "title": "Chief Financial Officer",
      "content": "Hi, Chad.",
      "sentiment": "0.0"
    },
    {
      "speaker": "Chad Dillard",
      "title": "Analyst",
      "content": "I wanted to revisit the comments about pricing in CI. First, I would like to understand when you expect to experience the maximum pricing pressure. Secondly, considering the cost side, you have declining fuel prices, and it seems you're reducing SG&A and R&D expenses. I'm trying to determine if you will be able to counter some of that pricing pressure with improved costs.",
      "sentiment": "0.1"
    },
    {
      "speaker": "Andrew Bonfield",
      "title": "Chief Financial Officer",
      "content": "Let me start by discussing the overall situation. Our gross margins for the quarter remained stable despite low volumes, as we were able to find offsets. Part of this is due to positive pricing in E&T and some reductions in manufacturing costs. Having a diverse portfolio of businesses helps us manage this effectively. We are monitoring commodity input costs and working on procurement, but it's important to remember that there is always a lag. We generally don\u2019t purchase at spot prices; instead, we buy at contracted prices, which can sometimes be lower than spot prices. All these factors contribute to a delayed effect. Regarding pricing pressure, the merchandising programs we've implemented are already impacting the P&L within CI. However, the lag I mentioned pertains to the reserve we have, which will only affect our balance sheet and impact us over the coming quarters. We will provide further updates in January.",
      "sentiment": "0.2"
    },
    {
      "speaker": "Operator",
      "title": "Operator",
      "content": "Next, we'll go to Tim Thein at Raymond James.",
      "sentiment": "0.0"
    },
    {
      "speaker": "Tim Thein",
      "title": "Analyst",
      "content": "Thank you. Good morning. Jim, could you provide some insight into the backlog and the strong orders from this quarter? What are the key factors driving that? Additionally, I'm interested to know if data centers will be a focus in this discussion and whether there is a change in how we should view the timing of deliveries, considering the tight capacity. I assume that some of your larger data center customers are trying to secure capacity well in advance. So, could you clarify what is driving these orders and if we should expect any changes in the delivery schedule? Thank you.",
      "sentiment": "0.2"
    },
    {
      "speaker": "Jim Umpleby",
      "title": "Chairman and CEO",
      "content": "Yeah. Thanks for your question. So, the backlog increase in Energy & Transportation was quite robust and that more than offset a decrease in backlog for Machines. And of course, it's not surprising that the backlog for Machines went down in anticipation of the machine dealer inventory reduction that we previously talked about in the fourth quarter. So, the backlog increase in Energy & Transportation being driven a lot by, of course, by power generation for recip, also being driven by robust orders in solar turbines for both oil and gas and recip. So that's really what's behind it. And so certainly, typically lead times for solar is eight to 12 months typically for recip and power generation. We're working hard to meet the demands of our customers there, but we do have orders going out 18, 24 months on the outside for power generation and recip.",
      "sentiment": "0.4"
    },
    {
      "speaker": "Operator",
      "title": "Operator",
      "content": "Next, we'll move to Mig Dobre at Baird.",
      "sentiment": "0.0"
    },
    {
      "speaker": "Mig Dobre",
      "title": "Analyst",
      "content": "Yes. Thank you. And just to follow-up on Tim's question, is there a way to maybe quantify what percentage of the backlog is deliverable here in the next 12 months? And I'm also curious, given the fact that the lead times are what they are in power gen, how are competitive dynamics, you versus your competitors, in that part of the business? Is there somebody else out there maybe with better lead times than you? Can you gain share if you improve your lead times faster than others? Appreciate some thoughts on that.",
      "sentiment": "0.2"
    },
    {
      "speaker": "Jim Umpleby",
      "title": "Chairman and CEO",
      "content": "You bet. Generally, overall, the way we think about it is about 75% of our backlog is expected to be sold within 12 months. That's a general number for total. As I mentioned, some of the large engine orders are out a bit more than that. Certainly, if we can produce more engines, we can sell more engines for power generation, recip engines. That's certainly the case. And again, just given the strength that we see in that market is obviously why we decided to make an incremental investment in our capability to increase engines and parts. So, again, the business is quite strong. It's very, very encouraging.",
      "sentiment": "0.4"
    },
    {
      "speaker": "Operator",
      "title": "Operator",
      "content": "Next, we'll go to Jairam Nathan at Daiwa.",
      "sentiment": "0.0"
    },
    {
      "speaker": "Jairam Nathan",
      "title": "Analyst",
      "content": "Yeah. Hi. Thanks for taking my question. I just wanted to go over some of your position in China. There's a lot of talk about stimulus, not sure how helpful it could be. But, if you could just remind us of your market position there, the freshness products a little bit?",
      "sentiment": "0.0"
    },
    {
      "speaker": "Jim Umpleby",
      "title": "Chairman and CEO",
      "content": "Certainly. As we've mentioned in the past, China has represented about 5% to 10% of our total sales and revenues for an extended period. However, it has fallen below that threshold in recent years, and the overall market remains quite weak. This year, it is again below 5%, making it a relatively small portion of our overall sales. We do have a strong presence in China with our facilities, supply chain integration, manufacturing, local leadership, and dealers. Nonetheless, the market is significantly depressed, especially for excavators over 10 tons. Regarding the stimulus, it's still too early for us to see any effects, and we haven't observed any changes yet.",
      "sentiment": "-0.3"
    },
    {
      "speaker": "Ryan Fiedler",
      "title": "Vice President of Investor Relations",
      "content": "Audra, we have time for one more question.",
      "sentiment": "0.0"
    },
    {
      "speaker": "Operator",
      "title": "Operator",
      "content": "And today's final question comes from the line of Rob Wertheimer with Melius Research.",
      "sentiment": "0.0"
    },
    {
      "speaker": "Rob Wertheimer",
      "title": "Analyst",
      "content": "Thank you. Good morning. I wanted to follow up on your comments from last quarter regarding the expanding opportunities at solar turbines and power generation. In today's call, you mentioned the strong demand in reciprocating engines and capacity expansion. On Renova's call, they noted positive trends in narrow derivative turbines, which may still be slightly above your power range. Could you discuss the opportunities in the power generation segment for solar? Specifically, what does that entail? Are we talking about behind-the-gate data centers or just data centers in general? Also, since you've expanded capacity in reciprocating engines, is there potential for growth in turbines, or is the market opportunity significant enough to consider expansion there as well? Just a general overview would be helpful. Thank you.",
      "sentiment": "0.2"
    },
    {
      "speaker": "Jim Umpleby",
      "title": "Chairman and CEO",
      "content": "Certainly. We are experiencing growth in our power generation and solar turbine businesses. We are currently selling trailerized units, driven by various factors. One key initiative involves selling to rental fleets, which are preparing to meet what they anticipate will be rising electricity demand, particularly in North America. These units may be rented by utilities or data centers, reflecting a range of applications. We are witnessing an increase in power generation, and solar has not reached its capacity limits; they can continue to boost production. Additionally, we are in the process of introducing our largest gas turbine for solar turbines, called the Titan 350. This product will enable us to compete in markets where we previously lacked a suitably large turbine. We are excited about this new offering, and although it's still early in the shipping process, we are encouraged by the strong interest and discussions we are having with customers about it. I want to express my gratitude to everyone for attending, and I appreciate your questions. I also want to thank our global team for achieving a strong adjusted operating profit margin and profit per share while generating healthy cash flow. As we've discussed, our results highlight the benefits of market diversity and the effective execution of our long-term growth strategy. Thank you again for your time.",
      "sentiment": "0.5"
    },
    {
      "speaker": "Ryan Fiedler",
      "title": "Vice President of Investor Relations",
      "content": "Thank you, Jim, Andrew, and everyone who joined us today. A replay of our call will be available online later this morning. We'll also post a transcript to our Investor Relations website as soon as it's available. You'll also find the third quarter results video with our CFO and an SEC filing with our sales to users data. Click on investors.caterpillar.com, then click on Financials to view those materials. If you have any questions, please reach out to Alex, Rob, or me. The Investor Relations general phone number is 309-675-4549. And now, we'll turn the call back to Audra to conclude.",
      "sentiment": "0.0"
    },
    {
      "speaker": "Operator",
      "title": "Operator",
      "content": "Thank you. That does conclude our call. Thank you for joining. You may all disconnect.",
      "sentiment": "0.0"
    }
  ],
  "reported_date": "2024-10-30"
}